fittrackee/__init__.py
fittrackee/__main__.py
fittrackee/application/__init__.py
fittrackee/application/app_config.py
fittrackee/application/exceptions.py
fittrackee/application/models.py
fittrackee/application/utils.py
fittrackee/cli/__init__.py
fittrackee/cli/app.py
fittrackee/comments/__init__.py
fittrackee/comments/comments.py
fittrackee/comments/decorators.py
fittrackee/comments/exceptions.py
fittrackee/comments/models.py
fittrackee/comments/utils.py
fittrackee/config.py
fittrackee/constants.py
fittrackee/database.py
fittrackee/dates.py
fittrackee/dist/favicon.ico
fittrackee/dist/img/bike.svg
fittrackee/dist/img/icons/android-chrome-192x192.png
fittrackee/dist/img/icons/android-chrome-512x512.png
fittrackee/dist/img/icons/android-chrome-maskable-192x192.png
fittrackee/dist/img/icons/android-chrome-maskable-512x512.png
fittrackee/dist/img/icons/apple-touch-icon-120x120.png
fittrackee/dist/img/icons/apple-touch-icon-152x152.png
fittrackee/dist/img/icons/apple-touch-icon-180x180.png
fittrackee/dist/img/icons/apple-touch-icon-60x60.png
fittrackee/dist/img/icons/apple-touch-icon-76x76.png
fittrackee/dist/img/icons/apple-touch-icon.png
fittrackee/dist/img/icons/favicon-16x16.png
fittrackee/dist/img/icons/favicon-32x32.png
fittrackee/dist/img/icons/msapplication-icon-144x144.png
fittrackee/dist/img/icons/mstile-150x150.png
fittrackee/dist/img/icons/safari-pinned-tab.svg
fittrackee/dist/img/user.png
fittrackee/dist/img/weather/breeze.svg
fittrackee/dist/img/weather/clear-day.svg
fittrackee/dist/img/weather/clear-night.svg
fittrackee/dist/img/weather/cloudy.svg
fittrackee/dist/img/weather/fog.svg
fittrackee/dist/img/weather/partly-cloudy-day.svg
fittrackee/dist/img/weather/partly-cloudy-night.svg
fittrackee/dist/img/weather/pour-rain.svg
fittrackee/dist/img/weather/rain.svg
fittrackee/dist/img/weather/sleet.svg
fittrackee/dist/img/weather/snow.svg
fittrackee/dist/img/weather/temperature.svg
fittrackee/dist/img/weather/wind.svg
fittrackee/dist/img/workouts/cadence.svg
fittrackee-1.1.0.dist-info/METADATA
fittrackee-1.1.0.dist-info/WHEEL
fittrackee-1.1.0.dist-info/entry_points.txt
fittrackee-1.1.0.dist-info/licenses/LICENSE
fittrackee-1.1.0.dist-info/RECORD
