Metadata-Version: 2.4
Name: fittrackee
Version: 1.1.0
Summary: Self-hosted outdoor workout/activity tracker
License: AGPL-3.0-only
License-File: LICENSE
Author: SamR1
Requires-Python: >=3.10,<4.0
Classifier: Development Status :: 5 - Production/Stable
Classifier: Environment :: Web Environment
Classifier: Framework :: Flask
Classifier: License :: OSI Approved :: GNU Affero General Public License v3
Classifier: Operating System :: POSIX :: Linux
Classifier: Programming Language :: JavaScript
Classifier: Programming Language :: Python :: 3
Classifier: Programming Language :: Python :: 3.10
Classifier: Programming Language :: Python :: 3.11
Classifier: Programming Language :: Python :: 3.12
Classifier: Programming Language :: Python :: 3.13
Classifier: Programming Language :: Python :: 3.14
Requires-Dist: authlib (==1.6.6)
Requires-Dist: babel (>=2.11.0,<3.0.0)
Requires-Dist: click (>=8.3.1,<9.0.0)
Requires-Dist: dramatiq-abort[redis] (>=1.2.1,<2.0.0)
Requires-Dist: dramatiq[redis] (>=1.15.0,<2.0.0)
Requires-Dist: feedgenerator (>=2.2.1,<3.0.0)
Requires-Dist: fitdecode (==0.11.0)
Requires-Dist: flask (>=3.1.2,<4.0.0)
Requires-Dist: flask-babel (>=4.0.0,<5.0.0)
Requires-Dist: flask-bcrypt (>=1.0.1,<2.0.0)
Requires-Dist: flask-dramatiq (>=0.6.0,<0.7.0)
Requires-Dist: flask-limiter[redis] (>=4.0.0,<5.0.0)
Requires-Dist: flask-migrate (==4.1.0)
Requires-Dist: flask-sqlalchemy (==3.1.1)
Requires-Dist: geoalchemy2[shapely] (>=0.18.1,<0.19.0)
Requires-Dist: geopandas (==1.1.1)
Requires-Dist: gpxpy (==1.6.2)
Requires-Dist: gunicorn (>=23.0.0,<24.0.0)
Requires-Dist: humanize (>=4.15.0,<5.0.0)
Requires-Dist: jsonschema (>=4.26.0,<5.0.0)
Requires-Dist: lxml (>=6.0.2,<7.0.0)
Requires-Dist: mistune (>=3.2.0,<4.0.0)
Requires-Dist: nh3 (>=0.3.2,<0.4.0)
Requires-Dist: numpy (==2.2.6)
Requires-Dist: pandas (==2.3.2)
Requires-Dist: psycopg2-binary (>=2.9.11,<3.0.0)
Requires-Dist: pyjwt (>=2.10.1,<3.0.0)
Requires-Dist: pyopenssl (>=25.3.0,<26.0.0)
Requires-Dist: pyproj (==3.7.1)
Requires-Dist: pytz (>=2025.2,<2026.0)
Requires-Dist: shortuuid (>=1.0.13,<2.0.0)
Requires-Dist: sqlalchemy (==2.0.45)
Requires-Dist: staticmap3[filecache] (>=0.1.0,<0.2.0)
Requires-Dist: ua-parser (>=1.0.0,<2.0.0)
Requires-Dist: xmltodict (>=1.0.2,<2.0.0)
Project-URL: Changelog, https://docs.fittrackee.org/en/changelog.html
Project-URL: Documentation, https://docs.fittrackee.org
Project-URL: Homepage, https://github.com/SamR1/FitTrackee
Project-URL: Issues, https://github.com/SamR1/FitTrackee/issues
Project-URL: Release Notes, https://github.com/SamR1/FitTrackee/releases
